llama_index/packs/cohere_citation_chat/__init__.py
llama_index/packs/cohere_citation_chat/base.py
llama_index/packs/cohere_citation_chat/citations_context_chat_engine.py
llama_index/packs/cohere_citation_chat/types.py
llama_index/packs/cohere_citation_chat/utils.py
llama_index_packs_cohere_citation_chat-0.5.1.dist-info/METADATA
llama_index_packs_cohere_citation_chat-0.5.1.dist-info/WHEEL
llama_index_packs_cohere_citation_chat-0.5.1.dist-info/licenses/LICENSE
llama_index_packs_cohere_citation_chat-0.5.1.dist-info/RECORD
