Metadata-Version: 2.4
Name: llama-index-packs-cohere-citation-chat
Version: 0.5.1
Summary: llama-index packs cohere_citation_chat integration
Author-email: Your Name <you@example.com>
Maintainer: EugeneLightsOn
License-Expression: MIT
License-File: LICENSE
Keywords: chat,citation,cite,cohere,engine,index
Requires-Python: <4.0,>=3.9
Requires-Dist: boto3<2,>=1.35.3
Requires-Dist: llama-index-core<0.15,>=0.13.0
Requires-Dist: llama-index-embeddings-cohere<0.7,>=0.6.0
Requires-Dist: llama-index-llms-cohere<0.7,>=0.6.0
